midi_generator/genetic.py
midi_generator/cli/__init__.py
midi_generator/cli/__main__.py
midi_generator/cli/commands.py
midi_generator/config/__init__.py
midi_generator/config/config.py
midi_generator/config/parser.py
midi_generator/utils/__init__.py
midi_generator/utils/constants.py
midi_generator/utils/math.py
midi_generator/utils/output.py
midi_generator/utils/scale.py
midi_generator/utils/syncopation.py
midi_generator-0.2.0.dist-info/LICENSE
midi_generator-0.2.0.dist-info/METADATA
midi_generator-0.2.0.dist-info/WHEEL
midi_generator-0.2.0.dist-info/entry_points.txt
midi_generator-0.2.0.dist-info/top_level.txt
midi_generator-0.2.0.dist-info/RECORD
