Metadata-Version: 2.1
Name: midi-generator
Version: 0.2.0
Summary: MIDI Generator for Python using genetic algorithms
Author-email: Gheorghe Andrei <gheorgheandrei13@gmail.com>
License: Copyright (c) 2022 Gheorghe Andrei        
Project-URL: Homepage, https://github.com/speedypleath/midi_generator
Keywords: midi,music,music generation,genetic algorithms
Classifier: Development Status :: 2 - Pre-Alpha
Classifier: Programming Language :: Python :: 3
Classifier: Topic :: Multimedia :: Sound/Audio :: MIDI
Classifier: Operating System :: OS Independent
Requires-Python: >=3.10
License-File: LICENSE
Requires-Dist: midiutil
Requires-Dist: numpy
Requires-Dist: matplotlib
Requires-Dist: seaborn
Requires-Dist: deap
Requires-Dist: aenum
Requires-Dist: pytest
